MANIFEST.in
README.txt
setup.py
QProcessing.egg-info/PKG-INFO
QProcessing.egg-info/SOURCES.txt
QProcessing.egg-info/dependency_links.txt
QProcessing.egg-info/top_level.txt
visualphysics/Layout.py
visualphysics/LayoutTest.py
visualphysics/RunProcessing.py
visualphysics/RunProcessingTest.py
visualphysics/__init__.py
visualphysics/processing-py.jar
visualphysics/visualphysics_test.py
visualphysics/layout/ButtonTable.py
visualphysics/layout/ButtonTableTest.py
visualphysics/layout/Frame.py
visualphysics/layout/FrameTest.py
visualphysics/layout/Grid.py
visualphysics/layout/GridTest.py
visualphysics/layout/Gutter.py
visualphysics/layout/GutterTest.py
visualphysics/layout/__init__.py