Metadata-Version: 1.1
Name: QProcessing
Version: 0.3.3
Summary: Visual Physics App to see the math of Nature 
Home-page: http://qprocessing.atlassian.net
Author: Doug Sweetser
Author-email: sweetser@alum.mit.edu
License: Apache-2.0
Keywords: visual physics analytic animation quaternion processing
Platform: UNKNOWN
Classifier: Development Status :: 3 - Alpha
Classifier: Topic :: Utilities
Classifier: License :: OSI Approved :: Apache Software License
